cv2multilinewrite/README.MD
cv2multilinewrite/__init__.py
cv2multilinewrite/requirements.txt
cv2multilinewrite/thirdparty.json
cv2multilinewrite-0.10.dist-info/LICENSE.rst
cv2multilinewrite-0.10.dist-info/METADATA
cv2multilinewrite-0.10.dist-info/WHEEL
cv2multilinewrite-0.10.dist-info/top_level.txt
cv2multilinewrite-0.10.dist-info/RECORD
