Metadata-Version: 2.1
Name: cv2multilinewrite
Version: 0.10
Summary: cv2.putText with new lines
Home-page: https://github.com/hansalemaos/cv2multilinewrite
Author: Johannes Fischer
Author-email: aulasparticularesdealemaosp@gmail.com
License: MIT
Keywords: cv2,putText
Classifier: Development Status :: 4 - Beta
Classifier: Programming Language :: Python :: 3 :: Only
Classifier: Programming Language :: Python :: 3.10
Classifier: Topic :: Software Development :: Libraries :: Python Modules
Classifier: Topic :: Utilities
License-File: LICENSE.rst
Requires-Dist: numpy
Requires-Dist: opencv-python
